mauna_graphql/common/answer_multiple_choice.graphql
mauna_graphql/common/answer_question.graphql
mauna_graphql/common/chitchat.graphql
mauna_graphql/common/classify_topic.graphql
mauna_graphql/common/commonsense_reasoning.graphql
mauna_graphql/common/get_conceptnet_relations.graphql
mauna_graphql/common/get_sentiment.graphql
mauna_graphql/common/match_intent.graphql
mauna_graphql/common/measure_similarity.graphql
mauna_graphql/common/paraphrase_sentence.graphql
mauna_graphql/common/parse_ace.graphql
mauna_graphql/common/parse_context.graphql
mauna_graphql/common/parse_text.graphql
mauna_graphql/common/parse_text_tokens.graphql
mauna_graphql/common/predict_next_turn.graphql
mauna_graphql/common/render_css.graphql
mauna_graphql/common/resolve_coreferences.graphql
mauna_graphql/common/speech_to_text.graphql
mauna_graphql/common/text_to_speech.graphql
mauna_graphql/common/to_vec.graphql
mauna_graphql/schema.graphql
mauna_sdk/__init__.py
mauna_sdk/api/__init__.py
mauna_sdk/api/answer_multiple_choice.py
mauna_sdk/api/answer_question.py
mauna_sdk/api/chitchat.py
mauna_sdk/api/classify_topic.py
mauna_sdk/api/commonsense_reasoning.py
mauna_sdk/api/enum/__init__.py
mauna_sdk/api/enum/a_c_e_output_type.py
mauna_sdk/api/enum/agent.py
mauna_sdk/api/enum/category.py
mauna_sdk/api/enum/relation.py
mauna_sdk/api/get_conceptnet_relations.py
mauna_sdk/api/get_sentiment.py
mauna_sdk/api/input/__init__.py
mauna_sdk/api/input/turn.py
mauna_sdk/api/match_intent.py
mauna_sdk/api/measure_similarity.py
mauna_sdk/api/paraphrase_sentence.py
mauna_sdk/api/parse_ace.py
mauna_sdk/api/parse_context.py
mauna_sdk/api/parse_text.py
mauna_sdk/api/parse_text_tokens.py
mauna_sdk/api/predict_next_turn.py
mauna_sdk/api/render_css.py
mauna_sdk/api/resolve_coreferences.py
mauna_sdk/api/speech_to_text.py
mauna_sdk/api/text_to_speech.py
mauna_sdk/api/to_vec.py
mauna_sdk/config.py
mauna_sdk/schema_config/json_scalar.py
mauna_sdk/token_cache.py
mauna_sdk/utils.py
mauna_sdk-0.2.21.dist-info/entry_points.txt
mauna_sdk-0.2.21.dist-info/LICENSE
mauna_sdk-0.2.21.dist-info/WHEEL
mauna_sdk-0.2.21.dist-info/METADATA
mauna_sdk-0.2.21.dist-info/RECORD
