Metadata-Version: 2.1
Name: mauna-sdk
Version: 0.2.21
Summary: Mauna SDK
License: ISC
Author: Dmitry Paramonov
Author-email: asmatic075@gmail.com
Requires-Python: >=3.6,<4.0
Classifier: License :: OSI Approved
Classifier: Programming Language :: Python :: 3
Classifier: Programming Language :: Python :: 3.6
Classifier: Programming Language :: Python :: 3.7
Classifier: Programming Language :: Python :: 3.8
Classifier: Programming Language :: Python :: 3.9
Requires-Dist: cryptography (>=3.4.6,<4.0.0)
Requires-Dist: dataclasses (>=0.6,<0.7); python_version >= "3.6" and python_version < "3.7"
Requires-Dist: gql[all] (==3.0.0a5)
Requires-Dist: py-gql-client (>=1.0.1,<2.0.0)
Requires-Dist: requests (>=2.25.1,<3.0.0)
